fhir/uscore/STU4/__init__.py
fhir/uscore/STU4/helpers.py
fhir/uscore/STU4/extensions/__init__.py
fhir/uscore/STU4/extensions/uscorebirthsex.py
fhir/uscore/STU4/extensions/uscoreethnicity.py
fhir/uscore/STU4/extensions/uscorerace.py
fhir/uscore/STU4/profiles/__init__.py
fhir/uscore/STU4/profiles/uscorecondition.py
fhir/uscore/STU4/profiles/uscorelocation.py
fhir/uscore/STU4/profiles/uscoreorganization.py
fhir/uscore/STU4/profiles/uscorepatient.py
fhir/uscore/STU4/profiles/uscorepractitioner.py
fhir/uscore/STU4/profiles/uscorepractitionerrole.py
fhir/uscore/STU4/profiles/uscoresmokingstatus.py
fhir/uscore/STU4/profiles/uscorevitalsigns.py
fhir/uscore/STU4/tests/__init__.py
fhir/uscore/STU4/tests/test_uscorecondition.py
fhir/uscore/STU4/tests/test_uscorelocation.py
fhir/uscore/STU4/tests/test_uscoreorganization.py
fhir/uscore/STU4/tests/test_uscorepatient.py
fhir/uscore/STU4/tests/test_uscorepractitioner.py
fhir/uscore/STU4/tests/test_uscorepractitionerrole.py
fhir/uscore/STU4/tests/test_uscoresmokingstatus.py
fhir.uscore-0.1.2.dist-info/METADATA
fhir.uscore-0.1.2.dist-info/WHEEL
fhir.uscore-0.1.2.dist-info/top_level.txt
fhir.uscore-0.1.2.dist-info/RECORD
